LICENSE
MANIFEST.in
README.md
pyproject.toml
setup.py
cython/__init__.py
cython/km_basic_filter.c
cython/km_basic_filter.pxd
cython/km_basic_filter.pyx
cython/km_fasta.c
cython/km_fasta.pxd
cython/km_fasta.pyx
cython/km_reset.c
cython/km_reset.pxd
cython/km_reset.pyx
cython/km_select.pxd
cython/km_select.pyx
cython/km_unitig.c
cython/km_unitig.pxd
cython/km_unitig.pyx
cython/km_tools_wrappers/__init__.py
cython/km_tools_wrappers/km_basic_filter_wrapper.py
cython/km_tools_wrappers/km_fasta_wrapper.py
cython/km_tools_wrappers/km_unitig_wrapper.py
cython/km_tools_wrappers/__pycache__/__init__.cpython-312.pyc
cython/km_tools_wrappers/__pycache__/km_basic_filter_wrapper.cpython-312.pyc
cython/km_tools_wrappers/__pycache__/km_fasta_wrapper.cpython-312.pyc
cython/km_tools_wrappers/__pycache__/km_unitig_wrapper.cpython-312.pyc
cython/lib/include/common.h
cython/lib/include/khash.h
cython/lib/include/km_basic_filter.h
cython/lib/include/km_fasta.h
cython/lib/include/km_reset.h
cython/lib/include/km_unitig.h
cython/lib/include/kseq.h
cython/lib/src/km_basic_filter.c
cython/lib/src/km_diff.c
cython/lib/src/km_fasta.c
cython/lib/src/km_merge.c
cython/lib/src/km_reset.c
cython/lib/src/km_reverse.c
cython/lib/src/km_select.c
cython/lib/src/km_tools.c
cython/lib/src/km_unitig.c
kmat_tools/__init__.py
kmat_tools/__main__.py
kmat_tools/__version__.py
kmat_tools.egg-info/PKG-INFO
kmat_tools.egg-info/SOURCES.txt
kmat_tools.egg-info/dependency_links.txt
kmat_tools.egg-info/entry_points.txt
kmat_tools.egg-info/requires.txt
kmat_tools.egg-info/top_level.txt
kmat_tools/utils/__init__.py
kmat_tools/utils/utils.py