Metadata-Version: 2.1
Name: kmat_tools
Version: 0.0.14
Home-page: https://github.com/CamilaDuitama/kmat_tools
Author: Riccardo Vicedomini, Francesco Andreace, Camila Duitama
Author-email: cduitama@pasteur.fr
Project-URL: Bug Tracker, https://github.com/CamilaDuitama/kmat_tools/issues
Classifier: Programming Language :: Python :: 3
Classifier: License :: OSI Approved :: MIT License
Classifier: Operating System :: OS Independent
License-File: LICENSE
Requires-Dist: colorama
Requires-Dist: Cython
Requires-Dist: wheel
Requires-Dist: setuptools
